<?xml version="1.0" encoding="utf-8"?>
<Language Name="English">
  <LocaleResource>
    <Name>common.save</Name>
    <Value>Save</Value>
  </LocaleResource>
  <LocaleResource>
    <Name>common.create</Name>
    <Value>Create</Value>
  </LocaleResource>
  <LocaleResource>
    <Name>common.edit</Name>
    <Value>Edit</Value>
  </LocaleResource>
  <LocaleResource>
    <Name>common.delete</Name>
    <Value>Delete</Value>
  </LocaleResource>
  <LocaleResource>
    <Name>common.apply</Name>
    <Value>Apply</Value>
  </LocaleResource>
  <LocaleResource>
    <Name>common.clear</Name>
    <Value>Clear</Value>
  </LocaleResource>
  <LocaleResource>
    <Name>common.cancel</Name>
    <Value>Cancel</Value>
  </LocaleResource>
  <LocaleResource>
    <Name>common.search</Name>
    <Value>Search</Value>
  </LocaleResource>
  <LocaleResource>
    <Name>common.filters</Name>
    <Value>Filters</Value>
  </LocaleResource>
  <LocaleResource>
    <Name>common.actions</Name>
    <Value>Actions</Value>
  </LocaleResource>
  <LocaleResource>
    <Name>common.details</Name>
    <Value>Details</Value>
  </LocaleResource>
  <LocaleResource>
    <Name>common.dashboard</Name>
    <Value>Dashboard</Value>
  </LocaleResource>
  <LocaleResource>
    <Name>admin.menu.main</Name>
    <Value>Main</Value>
  </LocaleResource>
  <LocaleResource>
    <Name>admin.menu.administration</Name>
    <Value>Administration</Value>
  </LocaleResource>
  <LocaleResource>
    <Name>admin.menu.admin</Name>
    <Value>Admin</Value>
  </LocaleResource>
  <LocaleResource>
    <Name>admin.menu.owners</Name>
    <Value>Owners</Value>
  </LocaleResource>
  <LocaleResource>
    <Name>admin.menu.roles</Name>
    <Value>Roles &amp; Permissions</Value>
  </LocaleResource>
  <LocaleResource>
    <Name>admin.menu.settings</Name>
    <Value>Admin Settings</Value>
  </LocaleResource>
  <LocaleResource>
    <Name>common.general</Name>
    <Value>General</Value>
  </LocaleResource>
  <LocaleResource>
    <Name>common.related</Name>
    <Value>Related</Value>
  </LocaleResource>
  <LocaleResource>
    <Name>common.none</Name>
    <Value>None</Value>
  </LocaleResource>
  <LocaleResource>
    <Name>common.yes</Name>
    <Value>Yes</Value>
  </LocaleResource>
  <LocaleResource>
    <Name>common.no</Name>
    <Value>No</Value>
  </LocaleResource>
  <LocaleResource>
    <Name>common.loading</Name>
    <Value>Loading...</Value>
  </LocaleResource>
  <LocaleResource>
    <Name>common.fromdate</Name>
    <Value>From Date</Value>
  </LocaleResource>
  <LocaleResource>
    <Name>common.todate</Name>
    <Value>To Date</Value>
  </LocaleResource>
  <LocaleResource>
    <Name>common.dangerzone</Name>
    <Value>Danger Zone</Value>
  </LocaleResource>
  <LocaleResource>
    <Name>common.delete.cannotundo</Name>
    <Value>This action cannot be undone.</Value>
  </LocaleResource>
  <LocaleResource>
    <Name>admin.datatable.lengthmenu</Name>
    <Value>Show _MENU_ entries</Value>
  </LocaleResource>
  <LocaleResource>
    <Name>admin.datatable.info</Name>
    <Value>Showing _START_ to _END_ of _TOTAL_ entries</Value>
  </LocaleResource>
  <LocaleResource>
    <Name>admin.datatable.infoempty</Name>
    <Value>Showing 0 to 0 of 0 entries</Value>
  </LocaleResource>
  <LocaleResource>
    <Name>admin.datatable.infofiltered</Name>
    <Value>(filtered from _MAX_ total entries)</Value>
  </LocaleResource>
  <LocaleResource>
    <Name>admin.datatable.emptytable</Name>
    <Value>No data available in table</Value>
  </LocaleResource>
  <LocaleResource>
    <Name>admin.datatable.zerorecords</Name>
    <Value>No matching records found</Value>
  </LocaleResource>
  <LocaleResource>
    <Name>admin.datatable.search</Name>
    <Value>Search:</Value>
  </LocaleResource>
  <LocaleResource>
    <Name>admin.datatable.processing</Name>
    <Value>Loading...</Value>
  </LocaleResource>
  <LocaleResource>
    <Name>admin.datatable.paginate.first</Name>
    <Value>First</Value>
  </LocaleResource>
  <LocaleResource>
    <Name>admin.datatable.paginate.last</Name>
    <Value>Last</Value>
  </LocaleResource>
  <LocaleResource>
    <Name>admin.datatable.paginate.next</Name>
    <Value>Next</Value>
  </LocaleResource>
  <LocaleResource>
    <Name>admin.datatable.paginate.previous</Name>
    <Value>Previous</Value>
  </LocaleResource>
  <LocaleResource>
    <Name>admin.plant.title</Name>
    <Value>Plants</Value>
  </LocaleResource>
  <LocaleResource>
    <Name>admin.plant.create</Name>
    <Value>Create Plant</Value>
  </LocaleResource>
  <LocaleResource>
    <Name>admin.plant.edit</Name>
    <Value>Edit Plant</Value>
  </LocaleResource>
  <LocaleResource>
    <Name>admin.plant.delete</Name>
    <Value>Delete Plant</Value>
  </LocaleResource>
  <LocaleResource>
    <Name>admin.plant.delete.title</Name>
    <Value>Delete plant</Value>
  </LocaleResource>
  <LocaleResource>
    <Name>admin.plant.delete.confirm</Name>
    <Value>This plant will be permanently deleted.</Value>
  </LocaleResource>
  <LocaleResource>
    <Name>admin.plant.notifications.create.success</Name>
    <Value>Plant was created successfully.</Value>
  </LocaleResource>
  <LocaleResource>
    <Name>admin.plant.notifications.edit.success</Name>
    <Value>Plant was updated successfully.</Value>
  </LocaleResource>
  <LocaleResource>
    <Name>admin.plant.notifications.delete.success</Name>
    <Value>Plant was deleted successfully.</Value>
  </LocaleResource>
  <LocaleResource>
    <Name>admin.plant.search.placeholder</Name>
    <Value>Common name, scientific name, family</Value>
  </LocaleResource>
  <LocaleResource>
    <Name>admin.plant.fields.commonname</Name>
    <Value>Common Name</Value>
  </LocaleResource>
  <LocaleResource>
    <Name>admin.plant.fields.scientificname</Name>
    <Value>Scientific Name</Value>
  </LocaleResource>
  <LocaleResource>
    <Name>admin.plant.fields.family</Name>
    <Value>Family</Value>
  </LocaleResource>
  <LocaleResource>
    <Name>admin.plant.fields.category</Name>
    <Value>Category</Value>
  </LocaleResource>
  <LocaleResource>
    <Name>admin.plant.fields.growthtype</Name>
    <Value>Growth Type</Value>
  </LocaleResource>
  <LocaleResource>
    <Name>admin.plant.fields.sunrequirement</Name>
    <Value>Sun Requirement</Value>
  </LocaleResource>
  <LocaleResource>
    <Name>admin.plant.fields.waterrequirement</Name>
    <Value>Water Requirement</Value>
  </LocaleResource>
  <LocaleResource>
    <Name>admin.plant.fields.mintempcelsius</Name>
    <Value>Min Temperature (°C)</Value>
  </LocaleResource>
  <LocaleResource>
    <Name>admin.plant.fields.maxtempcelsius</Name>
    <Value>Max Temperature (°C)</Value>
  </LocaleResource>
  <LocaleResource>
    <Name>admin.plant.fields.isedible</Name>
    <Value>Edible</Value>
  </LocaleResource>
  <LocaleResource>
    <Name>admin.plant.fields.ismedicinal</Name>
    <Value>Medicinal</Value>
  </LocaleResource>
  <LocaleResource>
    <Name>admin.plant.fields.istoxic</Name>
    <Value>Toxic</Value>
  </LocaleResource>
  <LocaleResource>
    <Name>admin.plant.fields.generalnotes</Name>
    <Value>General Notes</Value>
  </LocaleResource>
  <LocaleResource>
    <Name>admin.plant.category.all</Name>
    <Value>All Categories</Value>
  </LocaleResource>
  <LocaleResource>
    <Name>admin.plant.grid.id</Name>
    <Value>ID</Value>
  </LocaleResource>
  <LocaleResource>
    <Name>admin.plant.grid.flags</Name>
    <Value>Flags</Value>
  </LocaleResource>
  <LocaleResource>
    <Name>admin.plant.category.shrub</Name>
    <Value>Shrub</Value>
  </LocaleResource>
  <LocaleResource>
    <Name>admin.plant.category.tree</Name>
    <Value>Tree</Value>
  </LocaleResource>
  <LocaleResource>
    <Name>admin.plant.category.climber</Name>
    <Value>Climber</Value>
  </LocaleResource>
  <LocaleResource>
    <Name>admin.plant.category.ornamental</Name>
    <Value>Ornamental</Value>
  </LocaleResource>
  <LocaleResource>
    <Name>admin.plant.category.edible</Name>
    <Value>Edible</Value>
  </LocaleResource>
  <LocaleResource>
    <Name>admin.plant.category.aromatic</Name>
    <Value>Aromatic</Value>
  </LocaleResource>
  <LocaleResource>
    <Name>admin.plant.category.succulent</Name>
    <Value>Succulent</Value>
  </LocaleResource>
  <LocaleResource>
    <Name>admin.plant.category.grass</Name>
    <Value>Grass</Value>
  </LocaleResource>
  <LocaleResource>
    <Name>admin.plant.category.fern</Name>
    <Value>Fern</Value>
  </LocaleResource>
  <LocaleResource>
    <Name>admin.plant.category.other</Name>
    <Value>Other</Value>
  </LocaleResource>
  <LocaleResource>
    <Name>admin.plant.growthtype.annual</Name>
    <Value>Annual</Value>
  </LocaleResource>
  <LocaleResource>
    <Name>admin.plant.growthtype.biennial</Name>
    <Value>Biennial</Value>
  </LocaleResource>
  <LocaleResource>
    <Name>admin.plant.growthtype.perennial</Name>
    <Value>Perennial</Value>
  </LocaleResource>
  <LocaleResource>
    <Name>admin.plant.growthtype.bulb</Name>
    <Value>Bulb</Value>
  </LocaleResource>
  <LocaleResource>
    <Name>admin.plant.sunrequirement.fullsun</Name>
    <Value>Full Sun</Value>
  </LocaleResource>
  <LocaleResource>
    <Name>admin.plant.sunrequirement.partialshade</Name>
    <Value>Partial Shade</Value>
  </LocaleResource>
  <LocaleResource>
    <Name>admin.plant.sunrequirement.fullshade</Name>
    <Value>Full Shade</Value>
  </LocaleResource>
  <LocaleResource>
    <Name>admin.plant.waterrequirement.low</Name>
    <Value>Low</Value>
  </LocaleResource>
  <LocaleResource>
    <Name>admin.plant.waterrequirement.moderate</Name>
    <Value>Moderate</Value>
  </LocaleResource>
  <LocaleResource>
    <Name>admin.plant.waterrequirement.high</Name>
    <Value>High</Value>
  </LocaleResource>
  <LocaleResource>
    <Name>admin.plant.flags.edible</Name>
    <Value>Edible</Value>
  </LocaleResource>
  <LocaleResource>
    <Name>admin.plant.flags.medicinal</Name>
    <Value>Medicinal</Value>
  </LocaleResource>
  <LocaleResource>
    <Name>admin.plant.flags.toxic</Name>
    <Value>Toxic</Value>
  </LocaleResource>
  <LocaleResource>
    <Name>admin.plant.growth.environment</Name>
    <Value>Growth and Environment</Value>
  </LocaleResource>

  <!-- ===== Fertilizer ===== -->
  <LocaleResource>
    <Name>admin.fertilizer.title</Name>
    <Value>Fertilizers</Value>
  </LocaleResource>
  <LocaleResource>
    <Name>admin.fertilizer.create</Name>
    <Value>New Fertilizer</Value>
  </LocaleResource>
  <LocaleResource>
    <Name>admin.fertilizer.edit</Name>
    <Value>Edit Fertilizer</Value>
  </LocaleResource>
  <LocaleResource>
    <Name>admin.fertilizer.delete</Name>
    <Value>Delete Fertilizer</Value>
  </LocaleResource>
  <LocaleResource>
    <Name>admin.fertilizer.delete.confirm</Name>
    <Value>This fertilizer will be permanently deleted.</Value>
  </LocaleResource>
  <LocaleResource>
    <Name>admin.fertilizer.notifications.create.success</Name>
    <Value>Fertilizer was created successfully.</Value>
  </LocaleResource>
  <LocaleResource>
    <Name>admin.fertilizer.notifications.edit.success</Name>
    <Value>Fertilizer was updated successfully.</Value>
  </LocaleResource>
  <LocaleResource>
    <Name>admin.fertilizer.notifications.delete.success</Name>
    <Value>Fertilizer was deleted successfully.</Value>
  </LocaleResource>
  <LocaleResource>
    <Name>admin.fertilizer.fields.name</Name>
    <Value>Name</Value>
  </LocaleResource>
  <LocaleResource>
    <Name>admin.fertilizer.fields.brand</Name>
    <Value>Brand</Value>
  </LocaleResource>
  <LocaleResource>
    <Name>admin.fertilizer.fields.fertilizertype</Name>
    <Value>Fertilizer Type</Value>
  </LocaleResource>
  <LocaleResource>
    <Name>admin.fertilizer.fields.npkratio</Name>
    <Value>NPK Ratio</Value>
  </LocaleResource>
  <LocaleResource>
    <Name>admin.fertilizer.fields.applicationmethod</Name>
    <Value>Application Method</Value>
  </LocaleResource>
  <LocaleResource>
    <Name>admin.fertilizer.fields.isorganic</Name>
    <Value>Organic</Value>
  </LocaleResource>
  <LocaleResource>
    <Name>admin.fertilizer.fields.notes</Name>
    <Value>Notes</Value>
  </LocaleResource>
  <LocaleResource>
    <Name>admin.fertilizer.grid.id</Name>
    <Value>ID</Value>
  </LocaleResource>
  <LocaleResource>
    <Name>admin.fertilizer.fertilizertype.organic</Name>
    <Value>Organic</Value>
  </LocaleResource>
  <LocaleResource>
    <Name>admin.fertilizer.fertilizertype.chemical</Name>
    <Value>Chemical</Value>
  </LocaleResource>
  <LocaleResource>
    <Name>admin.fertilizer.fertilizertype.mineral</Name>
    <Value>Mineral</Value>
  </LocaleResource>
  <LocaleResource>
    <Name>admin.fertilizer.fertilizertype.liquid</Name>
    <Value>Liquid</Value>
  </LocaleResource>
  <LocaleResource>
    <Name>admin.fertilizer.fertilizertype.granular</Name>
    <Value>Granular</Value>
  </LocaleResource>
  <LocaleResource>
    <Name>admin.fertilizer.fertilizertype.slowrelease</Name>
    <Value>Slow Release</Value>
  </LocaleResource>
  <LocaleResource>
    <Name>admin.fertilizer.applicationmethod.soil</Name>
    <Value>Soil</Value>
  </LocaleResource>
  <LocaleResource>
    <Name>admin.fertilizer.applicationmethod.foliar</Name>
    <Value>Foliar Spray</Value>
  </LocaleResource>
  <LocaleResource>
    <Name>admin.fertilizer.applicationmethod.drip</Name>
    <Value>Drip</Value>
  </LocaleResource>
  <LocaleResource>
    <Name>admin.fertilizer.applicationmethod.diluted</Name>
    <Value>Diluted Solution</Value>
  </LocaleResource>

  <!-- ===== Pesticide ===== -->
  <LocaleResource>
    <Name>admin.pesticide.title</Name>
    <Value>Pesticides</Value>
  </LocaleResource>
  <LocaleResource>
    <Name>admin.pesticide.create</Name>
    <Value>New Pesticide</Value>
  </LocaleResource>
  <LocaleResource>
    <Name>admin.pesticide.edit</Name>
    <Value>Edit Pesticide</Value>
  </LocaleResource>
  <LocaleResource>
    <Name>admin.pesticide.delete</Name>
    <Value>Delete Pesticide</Value>
  </LocaleResource>
  <LocaleResource>
    <Name>admin.pesticide.delete.confirm</Name>
    <Value>This pesticide will be permanently deleted.</Value>
  </LocaleResource>
  <LocaleResource>
    <Name>admin.pesticide.notifications.create.success</Name>
    <Value>Pesticide was created successfully.</Value>
  </LocaleResource>
  <LocaleResource>
    <Name>admin.pesticide.notifications.edit.success</Name>
    <Value>Pesticide was updated successfully.</Value>
  </LocaleResource>
  <LocaleResource>
    <Name>admin.pesticide.notifications.delete.success</Name>
    <Value>Pesticide was deleted successfully.</Value>
  </LocaleResource>
  <LocaleResource>
    <Name>admin.pesticide.fields.name</Name>
    <Value>Name</Value>
  </LocaleResource>
  <LocaleResource>
    <Name>admin.pesticide.fields.brand</Name>
    <Value>Brand</Value>
  </LocaleResource>
  <LocaleResource>
    <Name>admin.pesticide.fields.activeingredient</Name>
    <Value>Active Ingredient</Value>
  </LocaleResource>
  <LocaleResource>
    <Name>admin.pesticide.fields.pesticidetype</Name>
    <Value>Pesticide Type</Value>
  </LocaleResource>
  <LocaleResource>
    <Name>admin.pesticide.fields.applicationmethod</Name>
    <Value>Application Method</Value>
  </LocaleResource>
  <LocaleResource>
    <Name>admin.pesticide.fields.isorganic</Name>
    <Value>Organic</Value>
  </LocaleResource>
  <LocaleResource>
    <Name>admin.pesticide.fields.withholdingdays</Name>
    <Value>Withholding Days</Value>
  </LocaleResource>
  <LocaleResource>
    <Name>admin.pesticide.fields.safetynotes</Name>
    <Value>Safety Notes</Value>
  </LocaleResource>
  <LocaleResource>
    <Name>admin.pesticide.fields.notes</Name>
    <Value>Notes</Value>
  </LocaleResource>
  <LocaleResource>
    <Name>admin.pesticide.grid.id</Name>
    <Value>ID</Value>
  </LocaleResource>
  <LocaleResource>
    <Name>admin.pesticide.pesticidetype.fungicide</Name>
    <Value>Fungicide</Value>
  </LocaleResource>
  <LocaleResource>
    <Name>admin.pesticide.pesticidetype.insecticide</Name>
    <Value>Insecticide</Value>
  </LocaleResource>
  <LocaleResource>
    <Name>admin.pesticide.pesticidetype.herbicide</Name>
    <Value>Herbicide</Value>
  </LocaleResource>
  <LocaleResource>
    <Name>admin.pesticide.pesticidetype.acaricide</Name>
    <Value>Acaricide</Value>
  </LocaleResource>
  <LocaleResource>
    <Name>admin.pesticide.pesticidetype.bactericide</Name>
    <Value>Bactericide</Value>
  </LocaleResource>
  <LocaleResource>
    <Name>admin.pesticide.pesticidetype.biostimulant</Name>
    <Value>Biostimulant</Value>
  </LocaleResource>
  <LocaleResource>
    <Name>admin.pesticide.pesticidetype.other</Name>
    <Value>Other</Value>
  </LocaleResource>
  <LocaleResource>
    <Name>admin.pesticide.applicationmethod.spray</Name>
    <Value>Spray</Value>
  </LocaleResource>
  <LocaleResource>
    <Name>admin.pesticide.applicationmethod.soil</Name>
    <Value>Soil Application</Value>
  </LocaleResource>
  <LocaleResource>
    <Name>admin.pesticide.applicationmethod.drench</Name>
    <Value>Drench</Value>
  </LocaleResource>
  <LocaleResource>
    <Name>admin.pesticide.applicationmethod.granule</Name>
    <Value>Granule</Value>
  </LocaleResource>
  <LocaleResource>
    <Name>admin.pesticide.applicationmethod.systemic</Name>
    <Value>Systemic</Value>
  </LocaleResource>

  <!-- ===== Disease ===== -->
  <LocaleResource>
    <Name>admin.disease.title</Name>
    <Value>Diseases &amp; Pests</Value>
  </LocaleResource>
  <LocaleResource>
    <Name>admin.disease.create</Name>
    <Value>New Disease / Pest</Value>
  </LocaleResource>
  <LocaleResource>
    <Name>admin.disease.edit</Name>
    <Value>Edit Disease / Pest</Value>
  </LocaleResource>
  <LocaleResource>
    <Name>admin.disease.delete</Name>
    <Value>Delete</Value>
  </LocaleResource>
  <LocaleResource>
    <Name>admin.disease.delete.confirm</Name>
    <Value>This disease / pest entry will be permanently deleted.</Value>
  </LocaleResource>
  <LocaleResource>
    <Name>admin.disease.notifications.create.success</Name>
    <Value>Disease / pest was created successfully.</Value>
  </LocaleResource>
  <LocaleResource>
    <Name>admin.disease.notifications.edit.success</Name>
    <Value>Disease / pest was updated successfully.</Value>
  </LocaleResource>
  <LocaleResource>
    <Name>admin.disease.notifications.delete.success</Name>
    <Value>Disease / pest was deleted successfully.</Value>
  </LocaleResource>
  <LocaleResource>
    <Name>admin.disease.fields.name</Name>
    <Value>Name</Value>
  </LocaleResource>
  <LocaleResource>
    <Name>admin.disease.fields.diseasetype</Name>
    <Value>Type</Value>
  </LocaleResource>
  <LocaleResource>
    <Name>admin.disease.fields.symptoms</Name>
    <Value>Symptoms</Value>
  </LocaleResource>
  <LocaleResource>
    <Name>admin.disease.fields.affectedparts</Name>
    <Value>Affected Parts</Value>
  </LocaleResource>
  <LocaleResource>
    <Name>admin.disease.fields.preventionnotes</Name>
    <Value>Prevention Notes</Value>
  </LocaleResource>
  <LocaleResource>
    <Name>admin.disease.fields.notes</Name>
    <Value>Notes</Value>
  </LocaleResource>
  <LocaleResource>
    <Name>admin.disease.grid.id</Name>
    <Value>ID</Value>
  </LocaleResource>
  <LocaleResource>
    <Name>admin.disease.diseasetype.fungal</Name>
    <Value>Fungal</Value>
  </LocaleResource>
  <LocaleResource>
    <Name>admin.disease.diseasetype.bacterial</Name>
    <Value>Bacterial</Value>
  </LocaleResource>
  <LocaleResource>
    <Name>admin.disease.diseasetype.viral</Name>
    <Value>Viral</Value>
  </LocaleResource>
  <LocaleResource>
    <Name>admin.disease.diseasetype.pest</Name>
    <Value>Pest</Value>
  </LocaleResource>
  <LocaleResource>
    <Name>admin.disease.diseasetype.deficiency</Name>
    <Value>Nutrient Deficiency</Value>
  </LocaleResource>
  <LocaleResource>
    <Name>admin.disease.diseasetype.physiological</Name>
    <Value>Physiological</Value>
  </LocaleResource>
  <LocaleResource>
    <Name>admin.disease.diseasetype.other</Name>
    <Value>Other</Value>
  </LocaleResource>
  <LocaleResource>
    <Name>admin.disease.remedylinks.title</Name>
    <Value>Recommended Pesticides</Value>
  </LocaleResource>
  <LocaleResource>
    <Name>admin.disease.remedylink.add</Name>
    <Value>Add Pesticide Link</Value>
  </LocaleResource>
  <LocaleResource>
    <Name>admin.disease.remedylink.fields.pesticide</Name>
    <Value>Pesticide</Value>
  </LocaleResource>
  <LocaleResource>
    <Name>admin.disease.remedylink.fields.treatmenttype</Name>
    <Value>Treatment Type</Value>
  </LocaleResource>
  <LocaleResource>
    <Name>admin.disease.remedylink.fields.dosage</Name>
    <Value>Dosage</Value>
  </LocaleResource>
  <LocaleResource>
    <Name>admin.disease.remedylink.fields.frequency</Name>
    <Value>Frequency</Value>
  </LocaleResource>
  <LocaleResource>
    <Name>admin.disease.remedylink.fields.notes</Name>
    <Value>Notes</Value>
  </LocaleResource>
  <LocaleResource>
    <Name>admin.disease.treatmenttype.preventive</Name>
    <Value>Preventive</Value>
  </LocaleResource>
  <LocaleResource>
    <Name>admin.disease.treatmenttype.curative</Name>
    <Value>Curative</Value>
  </LocaleResource>

  <!-- ===== SoilMix ===== -->
  <LocaleResource>
    <Name>admin.soilmix.title</Name>
    <Value>Soil Mixes</Value>
  </LocaleResource>
  <LocaleResource>
    <Name>admin.soilmix.create</Name>
    <Value>New Soil Mix</Value>
  </LocaleResource>
  <LocaleResource>
    <Name>admin.soilmix.edit</Name>
    <Value>Edit Soil Mix</Value>
  </LocaleResource>
  <LocaleResource>
    <Name>admin.soilmix.delete</Name>
    <Value>Delete Soil Mix</Value>
  </LocaleResource>
  <LocaleResource>
    <Name>admin.soilmix.delete.confirm</Name>
    <Value>This soil mix will be permanently deleted.</Value>
  </LocaleResource>
  <LocaleResource>
    <Name>admin.soilmix.notifications.create.success</Name>
    <Value>Soil mix was created successfully.</Value>
  </LocaleResource>
  <LocaleResource>
    <Name>admin.soilmix.notifications.edit.success</Name>
    <Value>Soil mix was updated successfully.</Value>
  </LocaleResource>
  <LocaleResource>
    <Name>admin.soilmix.notifications.delete.success</Name>
    <Value>Soil mix was deleted successfully.</Value>
  </LocaleResource>
  <LocaleResource>
    <Name>admin.soilmix.grid.id</Name>
    <Value>ID</Value>
  </LocaleResource>
  <LocaleResource>
    <Name>admin.soilmix.fields.name</Name>
    <Value>Name</Value>
  </LocaleResource>
  <LocaleResource>
    <Name>admin.soilmix.fields.composition</Name>
    <Value>Composition</Value>
  </LocaleResource>
  <LocaleResource>
    <Name>admin.soilmix.fields.phmin</Name>
    <Value>pH Min</Value>
  </LocaleResource>
  <LocaleResource>
    <Name>admin.soilmix.fields.phmax</Name>
    <Value>pH Max</Value>
  </LocaleResource>
  <LocaleResource>
    <Name>admin.soilmix.fields.phrange</Name>
    <Value>pH Range</Value>
  </LocaleResource>
  <LocaleResource>
    <Name>admin.soilmix.fields.texture</Name>
    <Value>Texture</Value>
  </LocaleResource>
  <LocaleResource>
    <Name>admin.soilmix.fields.drainage</Name>
    <Value>Drainage</Value>
  </LocaleResource>
  <LocaleResource>
    <Name>admin.soilmix.fields.notes</Name>
    <Value>Notes</Value>
  </LocaleResource>
  <LocaleResource>
    <Name>admin.soilmix.texture.sandy</Name>
    <Value>Sandy</Value>
  </LocaleResource>
  <LocaleResource>
    <Name>admin.soilmix.texture.loamy</Name>
    <Value>Loamy</Value>
  </LocaleResource>
  <LocaleResource>
    <Name>admin.soilmix.texture.clay</Name>
    <Value>Clay</Value>
  </LocaleResource>
  <LocaleResource>
    <Name>admin.soilmix.texture.silty</Name>
    <Value>Silty</Value>
  </LocaleResource>
  <LocaleResource>
    <Name>admin.soilmix.texture.peaty</Name>
    <Value>Peaty</Value>
  </LocaleResource>
  <LocaleResource>
    <Name>admin.soilmix.texture.chalky</Name>
    <Value>Chalky</Value>
  </LocaleResource>
  <LocaleResource>
    <Name>admin.soilmix.drainage.poor</Name>
    <Value>Poor</Value>
  </LocaleResource>
  <LocaleResource>
    <Name>admin.soilmix.drainage.moderate</Name>
    <Value>Moderate</Value>
  </LocaleResource>
  <LocaleResource>
    <Name>admin.soilmix.drainage.good</Name>
    <Value>Good</Value>
  </LocaleResource>
  <LocaleResource>
    <Name>admin.soilmix.drainage.excellent</Name>
    <Value>Excellent</Value>
  </LocaleResource>
  <LocaleResource>
    <Name>admin.soilmix.ingredients.title</Name>
    <Value>Ingredients</Value>
  </LocaleResource>
  <LocaleResource>
    <Name>admin.soilmix.ingredient.add</Name>
    <Value>Add Ingredient</Value>
  </LocaleResource>
  <LocaleResource>
    <Name>admin.soilmix.ingredient.fields.soilingredient</Name>
    <Value>Soil Ingredient</Value>
  </LocaleResource>
  <LocaleResource>
    <Name>admin.soilmix.ingredient.fields.percentage</Name>
    <Value>Percentage (%)</Value>
  </LocaleResource>
  <LocaleResource>
    <Name>admin.soilmix.ingredient.fields.notes</Name>
    <Value>Notes</Value>
  </LocaleResource>
  <LocaleResource>
    <Name>admin.soilmix.ingredient.fields.ingredientname</Name>
    <Value>Ingredient Name</Value>
  </LocaleResource>
  <LocaleResource>
    <Name>admin.soilmix.ingredient.fields.ingredientdescription</Name>
    <Value>Description</Value>
  </LocaleResource>
  <LocaleResource>
    <Name>admin.soilmix.ingredient.add.existing</Name>
    <Value>Select Existing</Value>
  </LocaleResource>
  <LocaleResource>
    <Name>admin.soilmix.ingredient.add.new</Name>
    <Value>Create New</Value>
  </LocaleResource>
  <LocaleResource>
    <Name>admin.soilmix.ingredient.noavailable</Name>
    <Value>All available ingredients are already added to this mix.</Value>
  </LocaleResource>
  <LocaleResource>
    <Name>admin.soilmix.ingredient.notifications.update.success</Name>
    <Value>Ingredient updated successfully.</Value>
  </LocaleResource>

  <LocaleResource>
    <Name>admin.applog.title</Name>
    <Value>Application Logs</Value>
  </LocaleResource>
  <LocaleResource>
    <Name>admin.applog.breadcrumb</Name>
    <Value>App Logs</Value>
  </LocaleResource>
  <LocaleResource>
    <Name>admin.applog.delete.selected</Name>
    <Value>Delete Selected</Value>
  </LocaleResource>
  <LocaleResource>
    <Name>admin.applog.delete.all</Name>
    <Value>Delete All</Value>
  </LocaleResource>
  <LocaleResource>
    <Name>admin.applog.delete.all.title</Name>
    <Value>Delete all log entries</Value>
  </LocaleResource>
  <LocaleResource>
    <Name>admin.applog.delete.all.confirm</Name>
    <Value>This action will permanently delete all log entries.</Value>
  </LocaleResource>
  <LocaleResource>
    <Name>admin.applog.delete.all.confirmbutton</Name>
    <Value>Delete all</Value>
  </LocaleResource>
  <LocaleResource>
    <Name>admin.applog.filters.alllevels</Name>
    <Value>All Levels</Value>
  </LocaleResource>
  <LocaleResource>
    <Name>admin.applog.grid.selectallvisible</Name>
    <Value>Select all visible</Value>
  </LocaleResource>
  <LocaleResource>
    <Name>admin.applog.fields.id</Name>
    <Value>ID</Value>
  </LocaleResource>
  <LocaleResource>
    <Name>admin.applog.fields.level</Name>
    <Value>Level</Value>
  </LocaleResource>
  <LocaleResource>
    <Name>admin.applog.fields.category</Name>
    <Value>Category</Value>
  </LocaleResource>
  <LocaleResource>
    <Name>admin.applog.fields.message</Name>
    <Value>Message</Value>
  </LocaleResource>
  <LocaleResource>
    <Name>admin.applog.fields.timestamp</Name>
    <Value>Timestamp</Value>
  </LocaleResource>
  <LocaleResource>
    <Name>admin.applog.delete.selected.title</Name>
    <Value>Delete selected logs</Value>
  </LocaleResource>
  <LocaleResource>
    <Name>admin.applog.delete.selected.confirm</Name>
    <Value>This action will permanently delete {0} selected log entries.</Value>
  </LocaleResource>
  <LocaleResource>
    <Name>admin.applog.delete.selected.confirm.single</Name>
    <Value>This action will permanently delete 1 selected log entry.</Value>
  </LocaleResource>
  <LocaleResource>
    <Name>admin.applog.delete.selected.confirmbutton</Name>
    <Value>Delete selected</Value>
  </LocaleResource>
  <LocaleResource>
    <Name>admin.applog.delete.selected.success</Name>
    <Value>Selected log entries were deleted.</Value>
  </LocaleResource>
  <LocaleResource>
    <Name>admin.applog.delete.selected.error</Name>
    <Value>Failed to delete selected log entries.</Value>
  </LocaleResource>
  <LocaleResource>
    <Name>admin.applog.delete.single.title</Name>
    <Value>Delete log entry</Value>
  </LocaleResource>
  <LocaleResource>
    <Name>admin.applog.delete.single.confirm</Name>
    <Value>This log entry will be permanently deleted.</Value>
  </LocaleResource>
  <LocaleResource>
    <Name>admin.applog.delete.single.success</Name>
    <Value>Log entry deleted.</Value>
  </LocaleResource>
  <LocaleResource>
    <Name>admin.applog.delete.single.error</Name>
    <Value>Failed to delete the log entry.</Value>
  </LocaleResource>
  <LocaleResource>
    <Name>admin.localization.languages.title</Name>
    <Value>Languages</Value>
  </LocaleResource>
  <LocaleResource>
    <Name>admin.localization.language.create</Name>
    <Value>Create Language</Value>
  </LocaleResource>
  <LocaleResource>
    <Name>admin.localization.language.edit</Name>
    <Value>Edit Language</Value>
  </LocaleResource>
  <LocaleResource>
    <Name>admin.localization.language.delete</Name>
    <Value>Delete Language</Value>
  </LocaleResource>
  <LocaleResource>
    <Name>admin.localization.language.delete.confirm</Name>
    <Value>This language will be permanently deleted.</Value>
  </LocaleResource>
  <LocaleResource>
    <Name>admin.localization.language.create.success</Name>
    <Value>Language created successfully.</Value>
  </LocaleResource>
  <LocaleResource>
    <Name>admin.localization.language.edit.success</Name>
    <Value>Language updated successfully.</Value>
  </LocaleResource>
  <LocaleResource>
    <Name>admin.localization.language.delete.success</Name>
    <Value>Language deleted successfully.</Value>
  </LocaleResource>
  <LocaleResource>
    <Name>admin.localization.language.delete.hasresources</Name>
    <Value>Language cannot be deleted while it has resources.</Value>
  </LocaleResource>
  <LocaleResource>
    <Name>admin.localization.language.delete.hint</Name>
    <Value>Permanently deletes this language and all its locale resources. This action cannot be undone.</Value>
  </LocaleResource>
  <LocaleResource>
    <Name>admin.localization.language.fields.name</Name>
    <Value>Name</Value>
  </LocaleResource>
  <LocaleResource>
    <Name>admin.localization.language.fields.culture</Name>
    <Value>Culture</Value>
  </LocaleResource>
  <LocaleResource>
    <Name>admin.localization.language.fields.seocode</Name>
    <Value>SEO Code</Value>
  </LocaleResource>
  <LocaleResource>
    <Name>admin.localization.language.fields.flag</Name>
    <Value>Flag File Name</Value>
  </LocaleResource>
  <LocaleResource>
    <Name>admin.localization.language.fields.rtl</Name>
    <Value>RTL</Value>
  </LocaleResource>
  <LocaleResource>
    <Name>admin.localization.language.fields.published</Name>
    <Value>Published</Value>
  </LocaleResource>
  <LocaleResource>
    <Name>admin.localization.language.fields.displayorder</Name>
    <Value>Display Order</Value>
  </LocaleResource>
  <LocaleResource>
    <Name>admin.localization.language.fields.id</Name>
    <Value>ID</Value>
  </LocaleResource>
  <LocaleResource>
    <Name>admin.localization.language.manage</Name>
    <Value>Manage Resources</Value>
  </LocaleResource>
  <LocaleResource>
    <Name>admin.localization.resources.title</Name>
    <Value>Locale Resources</Value>
  </LocaleResource>
  <LocaleResource>
    <Name>admin.localization.resource.create</Name>
    <Value>Create Resource</Value>
  </LocaleResource>
  <LocaleResource>
    <Name>admin.localization.resource.edit</Name>
    <Value>Edit Resource</Value>
  </LocaleResource>
  <LocaleResource>
    <Name>admin.localization.resource.delete</Name>
    <Value>Delete Resource</Value>
  </LocaleResource>
  <LocaleResource>
    <Name>admin.localization.resource.delete.confirm</Name>
    <Value>This resource will be permanently deleted.</Value>
  </LocaleResource>
  <LocaleResource>
    <Name>admin.localization.resource.create.success</Name>
    <Value>Resource created successfully.</Value>
  </LocaleResource>
  <LocaleResource>
    <Name>admin.localization.resource.edit.success</Name>
    <Value>Resource updated successfully.</Value>
  </LocaleResource>
  <LocaleResource>
    <Name>admin.localization.resource.delete.success</Name>
    <Value>Resource deleted successfully.</Value>
  </LocaleResource>
  <LocaleResource>
    <Name>admin.localization.resource.export</Name>
    <Value>Export XML</Value>
  </LocaleResource>
  <LocaleResource>
    <Name>admin.localization.resource.import</Name>
    <Value>Import XML</Value>
  </LocaleResource>
  <LocaleResource>
    <Name>admin.localization.resource.import.success</Name>
    <Value>Resources imported successfully.</Value>
  </LocaleResource>
  <LocaleResource>
    <Name>admin.localization.resource.import.empty</Name>
    <Value>Please select a valid XML file.</Value>
  </LocaleResource>
  <LocaleResource>
    <Name>admin.localization.resource.import.updateexisting</Name>
    <Value>Update existing resources</Value>
  </LocaleResource>
  <LocaleResource>
    <Name>admin.localization.resource.fields.name</Name>
    <Value>Key</Value>
  </LocaleResource>
  <LocaleResource>
    <Name>admin.localization.resource.fields.value</Name>
    <Value>Value</Value>
  </LocaleResource>
  <LocaleResource>
    <Name>admin.dt.emptytable</Name>
    <Value>No data available in table</Value>
  </LocaleResource>
  <LocaleResource>
    <Name>admin.dt.info</Name>
    <Value>Showing _START_ to _END_ of _TOTAL_ entries</Value>
  </LocaleResource>
  <LocaleResource>
    <Name>admin.dt.infoempty</Name>
    <Value>Showing 0 to 0 of 0 entries</Value>
  </LocaleResource>
  <LocaleResource>
    <Name>admin.dt.infofiltered</Name>
    <Value>(filtered from _MAX_ total entries)</Value>
  </LocaleResource>
  <LocaleResource>
    <Name>admin.dt.thousands</Name>
    <Value>,</Value>
  </LocaleResource>
  <LocaleResource>
    <Name>admin.dt.lengthmenu</Name>
    <Value>Show _MENU_ entries</Value>
  </LocaleResource>
  <LocaleResource>
    <Name>admin.dt.loadingrecords</Name>
    <Value>Loading...</Value>
  </LocaleResource>
  <LocaleResource>
    <Name>admin.dt.loadericon</Name>
    <Value>Processing...</Value>
  </LocaleResource>
  <LocaleResource>
    <Name>admin.dt.search</Name>
    <Value>Search:</Value>
  </LocaleResource>
  <LocaleResource>
    <Name>admin.dt.zerorecords</Name>
    <Value>No matching records found</Value>
  </LocaleResource>
  <LocaleResource>
    <Name>admin.dt.paginate.first</Name>
    <Value>First</Value>
  </LocaleResource>
  <LocaleResource>
    <Name>admin.dt.paginate.last</Name>
    <Value>Last</Value>
  </LocaleResource>
  <LocaleResource>
    <Name>admin.dt.paginate.next</Name>
    <Value>Next</Value>
  </LocaleResource>
  <LocaleResource>
    <Name>admin.dt.paginate.previous</Name>
    <Value>Previous</Value>
  </LocaleResource>
  <LocaleResource>
    <Name>admin.dt.aria.sortascending</Name>
    <Value>: activate to sort column ascending</Value>
  </LocaleResource>
  <LocaleResource>
    <Name>admin.dt.aria.sortdescending</Name>
    <Value>: activate to sort column descending</Value>
  </LocaleResource>
  <LocaleResource>
    <Name>common.confirm.delete.title</Name>
    <Value>Delete</Value>
  </LocaleResource>
  <LocaleResource>
    <Name>common.confirm.delete.text</Name>
    <Value>Are you sure you want to delete this item?</Value>
  </LocaleResource>
  <LocaleResource>
    <Name>common.confirm.delete.items</Name>
    <Value>Are you sure you want to delete {0} items?</Value>
  </LocaleResource>
  <LocaleResource>
    <Name>common.profile</Name>
    <Value>Profile</Value>
  </LocaleResource>
  <LocaleResource>
    <Name>common.logout</Name>
    <Value>Logout</Value>
  </LocaleResource>
  <LocaleResource>
    <Name>common.login</Name>
    <Value>Login</Value>
  </LocaleResource>
  <LocaleResource>
    <Name>common.register</Name>
    <Value>Register</Value>
  </LocaleResource>
  <LocaleResource>
    <Name>common.user</Name>
    <Value>User</Value>
  </LocaleResource>
  <!-- Landing Page -->
  <LocaleResource>
    <Name>landing.page.title</Name>
    <Value>Garden Manager — Manage Your Garden</Value>
  </LocaleResource>
  <LocaleResource>
    <Name>landing.nav.home</Name>
    <Value>Home</Value>
  </LocaleResource>
  <LocaleResource>
    <Name>landing.nav.features</Name>
    <Value>Features</Value>
  </LocaleResource>
  <LocaleResource>
    <Name>landing.hero.title</Name>
    <Value>Manage your garden, every day.</Value>
  </LocaleResource>
  <LocaleResource>
    <Name>landing.hero.subtitle</Name>
    <Value>Track plants, schedule care, and log daily actions — all in one place.</Value>
  </LocaleResource>
  <LocaleResource>
    <Name>landing.hero.cta.start</Name>
    <Value>Get Started Free</Value>
  </LocaleResource>
  <LocaleResource>
    <Name>landing.features.badge</Name>
    <Value>Features</Value>
  </LocaleResource>
  <LocaleResource>
    <Name>landing.features.title</Name>
    <Value>Everything your garden needs</Value>
  </LocaleResource>
  <LocaleResource>
    <Name>landing.features.subtitle</Name>
    <Value>Simple, fast and reliable tools for daily plant care.</Value>
  </LocaleResource>
  <LocaleResource>
    <Name>landing.features.track.title</Name>
    <Value>Plant Tracking</Value>
  </LocaleResource>
  <LocaleResource>
    <Name>landing.features.track.desc</Name>
    <Value>Keep a record for each plant — location, container, soil mix and care history.</Value>
  </LocaleResource>
  <LocaleResource>
    <Name>landing.features.schedule.title</Name>
    <Value>Care Scheduling</Value>
  </LocaleResource>
  <LocaleResource>
    <Name>landing.features.schedule.desc</Name>
    <Value>Watering, fertilizing and repotting with a clear action history.</Value>
  </LocaleResource>
  <LocaleResource>
    <Name>landing.features.health.title</Name>
    <Value>Plant Health</Value>
  </LocaleResource>
  <LocaleResource>
    <Name>landing.features.health.desc</Name>
    <Value>Log diseases, manage treatments and track recovery progress.</Value>
  </LocaleResource>
  <LocaleResource>
    <Name>landing.cta.title</Name>
    <Value>Start today</Value>
  </LocaleResource>
  <LocaleResource>
    <Name>landing.cta.subtitle</Name>
    <Value>Register and start managing your garden right away.</Value>
  </LocaleResource>
  <LocaleResource>
    <Name>landing.footer.tagline</Name>
    <Value>Your digital base for a healthy garden.</Value>
  </LocaleResource>
  <LocaleResource>
    <Name>landing.footer.links</Name>
    <Value>Links</Value>
  </LocaleResource>
  <LocaleResource>
    <Name>landing.footer.rights</Name>
    <Value>All rights reserved.</Value>
  </LocaleResource>
  <!-- Dashboard placeholder -->
  <LocaleResource>
    <Name>dashboard.welcome</Name>
    <Value>Welcome to your garden!</Value>
  </LocaleResource>
  <LocaleResource>
    <Name>dashboard.coming.soon</Name>
    <Value>Your dashboard is coming in the next milestone.</Value>
  </LocaleResource>
  <LocaleResource>
    <Name>common.viewall</Name>
    <Value>View All</Value>
  </LocaleResource>
  <LocaleResource>
    <Name>dashboard.owner.title</Name>
    <Value>Today's Actions</Value>
  </LocaleResource>
  <LocaleResource>
    <Name>dashboard.owner.subtitle</Name>
    <Value>Your daily care cockpit for plants and garden routines.</Value>
  </LocaleResource>
  <LocaleResource>
    <Name>dashboard.owner.cta.myplants</Name>
    <Value>My Plants</Value>
  </LocaleResource>
  <LocaleResource>
    <Name>dashboard.owner.kpi.activeplants</Name>
    <Value>Active Plants</Value>
  </LocaleResource>
  <LocaleResource>
    <Name>dashboard.owner.kpi.actionstoday</Name>
    <Value>Due Today</Value>
  </LocaleResource>
  <LocaleResource>
    <Name>dashboard.owner.kpi.overdue</Name>
    <Value>Overdue</Value>
  </LocaleResource>
  <LocaleResource>
    <Name>dashboard.owner.kpi.activecases</Name>
    <Value>Active Disease Cases</Value>
  </LocaleResource>
  <LocaleResource>
    <Name>dashboard.owner.todayactions</Name>
    <Value>Overdue &amp; Today Actions</Value>
  </LocaleResource>
  <LocaleResource>
    <Name>dashboard.owner.todayactions.empty</Name>
    <Value>No overdue or due-today actions. Great job!</Value>
  </LocaleResource>
  <LocaleResource>
    <Name>dashboard.owner.recentactivity</Name>
    <Value>Recent Activity</Value>
  </LocaleResource>
  <LocaleResource>
    <Name>dashboard.owner.recentactivity.empty</Name>
    <Value>No activity recorded yet.</Value>
  </LocaleResource>
  <LocaleResource>
    <Name>dashboard.owner.tab.watering</Name>
    <Value>Watering</Value>
  </LocaleResource>
  <LocaleResource>
    <Name>dashboard.owner.tab.fertilizing</Name>
    <Value>Fertilizing</Value>
  </LocaleResource>
  <LocaleResource>
    <Name>dashboard.owner.tab.diseases</Name>
    <Value>Diseases</Value>
  </LocaleResource>
  <LocaleResource>
    <Name>dashboard.owner.tab.diseases.empty</Name>
    <Value>No active disease cases in your garden.</Value>
  </LocaleResource>
  <LocaleResource>
    <Name>dashboard.owner.filter.allspots</Name>
    <Value>All</Value>
  </LocaleResource>
  <LocaleResource>
    <Name>dashboard.owner.filter.label</Name>
    <Value>Filter</Value>
  </LocaleResource>
  <LocaleResource>
    <Name>dashboard.owner.disease.plant</Name>
    <Value>Plant</Value>
  </LocaleResource>
  <LocaleResource>
    <Name>dashboard.owner.disease.name</Name>
    <Value>Disease</Value>
  </LocaleResource>
  <LocaleResource>
    <Name>dashboard.owner.disease.location</Name>
    <Value>Location</Value>
  </LocaleResource>
  <LocaleResource>
    <Name>dashboard.owner.disease.diagnosed</Name>
    <Value>Diagnosed</Value>
  </LocaleResource>
  <LocaleResource>
    <Name>dashboard.owner.disease.severity</Name>
    <Value>Severity</Value>
  </LocaleResource>
  <LocaleResource>
    <Name>dashboard.owner.action.watering</Name>
    <Value>Watering</Value>
  </LocaleResource>
  <LocaleResource>
    <Name>dashboard.owner.action.fertilizing</Name>
    <Value>Fertilizing</Value>
  </LocaleResource>
  <LocaleResource>
    <Name>dashboard.owner.action.done</Name>
    <Value>Done</Value>
  </LocaleResource>
  <LocaleResource>
    <Name>dashboard.owner.action.skip</Name>
    <Value>Skip</Value>
  </LocaleResource>
  <LocaleResource>
    <Name>dashboard.owner.skip.title</Name>
    <Value>Skip this action</Value>
  </LocaleResource>
  <LocaleResource>
    <Name>dashboard.owner.skip.prompt</Name>
    <Value>What would you like to do with:</Value>
  </LocaleResource>
  <LocaleResource>
    <Name>dashboard.owner.skip.today</Name>
    <Value>Skip for today — remind me tomorrow</Value>
  </LocaleResource>
  <LocaleResource>
    <Name>dashboard.owner.skip.next</Name>
    <Value>Notify at next scheduled date</Value>
  </LocaleResource>
  <LocaleResource>
    <Name>dashboard.owner.status.overdue</Name>
    <Value>Overdue</Value>
  </LocaleResource>
  <LocaleResource>
    <Name>dashboard.owner.status.today</Name>
    <Value>Today</Value>
  </LocaleResource>
  <LocaleResource>
    <Name>dashboard.owner.status.upcoming</Name>
    <Value>Upcoming</Value>
  </LocaleResource>
  <LocaleResource>
    <Name>dashboard.owner.frequency</Name>
    <Value>Frequency:</Value>
  </LocaleResource>
  <LocaleResource>
    <Name>dashboard.owner.days</Name>
    <Value>days</Value>
  </LocaleResource>
  <!-- My Garden -->
  <LocaleResource>
    <Name>mygarden.menu.title</Name>
    <Value>My Garden</Value>
  </LocaleResource>
  <!-- Plant Instances -->
  <LocaleResource>
    <Name>mygarden.plantinstance.list.title</Name>
    <Value>My Plants</Value>
  </LocaleResource>
  <LocaleResource>
    <Name>mygarden.plantinstance.add</Name>
    <Value>Add Plant</Value>
  </LocaleResource>
  <LocaleResource>
    <Name>mygarden.plantinstance.create.title</Name>
    <Value>Add Plant</Value>
  </LocaleResource>
  <LocaleResource>
    <Name>mygarden.plantinstance.edit.title</Name>
    <Value>Edit Plant</Value>
  </LocaleResource>
  <LocaleResource>
    <Name>mygarden.plantinstance.edit.details</Name>
    <Value>Plant Details</Value>
  </LocaleResource>
  <LocaleResource>
    <Name>mygarden.plantinstance.list.empty</Name>
    <Value>No plants yet. Add your first plant to get started.</Value>
  </LocaleResource>
  <LocaleResource>
    <Name>mygarden.plantinstance.field.plant</Name>
    <Value>Plant</Value>
  </LocaleResource>
  <LocaleResource>
    <Name>mygarden.plantinstance.field.location</Name>
    <Value>Location</Value>
  </LocaleResource>
  <LocaleResource>
    <Name>mygarden.plantinstance.field.gardenspot</Name>
    <Value>Garden Spot</Value>
  </LocaleResource>
  <LocaleResource>
    <Name>mygarden.plantinstance.field.container</Name>
    <Value>Container</Value>
  </LocaleResource>
  <LocaleResource>
    <Name>mygarden.plantinstance.field.soilmix</Name>
    <Value>Soil Mix</Value>
  </LocaleResource>
  <LocaleResource>
    <Name>mygarden.plantinstance.field.nickname</Name>
    <Value>Nickname</Value>
  </LocaleResource>
  <LocaleResource>
    <Name>mygarden.plantinstance.field.planteddate</Name>
    <Value>Planted Date</Value>
  </LocaleResource>
  <LocaleResource>
    <Name>mygarden.plantinstance.field.age</Name>
    <Value>Age</Value>
  </LocaleResource>
  <LocaleResource>
    <Name>mygarden.plantinstance.field.size</Name>
    <Value>Size Category</Value>
  </LocaleResource>
  <LocaleResource>
    <Name>mygarden.plantinstance.field.height</Name>
    <Value>Height</Value>
  </LocaleResource>
  <LocaleResource>
    <Name>mygarden.plantinstance.field.spread</Name>
    <Value>Spread</Value>
  </LocaleResource>
  <LocaleResource>
    <Name>mygarden.plantinstance.field.health</Name>
    <Value>Health Status</Value>
  </LocaleResource>
  <LocaleResource>
    <Name>mygarden.plantinstance.field.active</Name>
    <Value>Active</Value>
  </LocaleResource>
  <LocaleResource>
    <Name>mygarden.plantinstance.filter.plant</Name>
    <Value>Plant</Value>
  </LocaleResource>
  <LocaleResource>
    <Name>mygarden.plantinstance.filter.location</Name>
    <Value>Location</Value>
  </LocaleResource>
  <LocaleResource>
    <Name>mygarden.plantinstance.filter.gardenspot</Name>
    <Value>Garden Spot</Value>
  </LocaleResource>
  <LocaleResource>
    <Name>mygarden.plantinstance.filter.activeonly</Name>
    <Value>Active Plants Only</Value>
  </LocaleResource>
  <LocaleResource>
    <Name>admin.picture.upload</Name>
    <Value>Upload Image</Value>
  </LocaleResource>
  <LocaleResource>
    <Name>admin.picture.remove</Name>
    <Value>Remove</Value>
  </LocaleResource>
  <LocaleResource>
    <Name>admin.picture.preview.alt</Name>
    <Value>Picture preview</Value>
  </LocaleResource>
  <LocaleResource>
    <Name>admin.picture.status.uploading</Name>
    <Value>Uploading…</Value>
  </LocaleResource>
  <LocaleResource>
    <Name>admin.picture.status.error</Name>
    <Value>Upload failed. Please try again.</Value>
  </LocaleResource>
  <LocaleResource>
    <Name>admin.plant.fields.picture</Name>
    <Value>Picture</Value>
  </LocaleResource>
  <LocaleResource>
    <Name>mygarden.gardenspot.field.picture</Name>
    <Value>Photo</Value>
  </LocaleResource>
  <LocaleResource>
    <Name>mygarden.plantinstance.photos.title</Name>
    <Value>Photos</Value>
  </LocaleResource>
  <LocaleResource>
    <Name>mygarden.plantinstance.photos.add</Name>
    <Value>Add Photo</Value>
  </LocaleResource>
  <LocaleResource>
    <Name>mygarden.plantinstance.photos.empty</Name>
    <Value>No photos yet. Upload the first one below.</Value>
  </LocaleResource>
  <LocaleResource>
    <Name>mygarden.plantinstance.photo.field.caption</Name>
    <Value>Caption</Value>
  </LocaleResource>
  <LocaleResource>
    <Name>mygarden.plantinstance.photo.field.takendate</Name>
    <Value>Taken Date</Value>
  </LocaleResource>
  <LocaleResource>
    <Name>mygarden.plantinstance.photo.field.displayorder</Name>
    <Value>Display Order</Value>
  </LocaleResource>
  <LocaleResource>
    <Name>mygarden.plantinstance.photo.field.thumbnail</Name>
    <Value>Photo</Value>
  </LocaleResource>
  <LocaleResource>
    <Name>mygarden.plantinstance.photo.delete.confirm</Name>
    <Value>Are you sure you want to delete this photo?</Value>
  </LocaleResource>
  <LocaleResource>
    <Name>mygarden.plantinstance.photo.add.success</Name>
    <Value>Photo added successfully.</Value>
  </LocaleResource>
  <LocaleResource>
    <Name>mygarden.plantinstance.photo.delete.success</Name>
    <Value>Photo deleted successfully.</Value>
  </LocaleResource>
  <LocaleResource>
    <Name>mygarden.plantinstance.photo.update.success</Name>
    <Value>Photo updated successfully.</Value>
  </LocaleResource>
  <LocaleResource>
    <Name>mygarden.plantinstance.photo.field.image</Name>
    <Value>Image</Value>
  </LocaleResource>
  <!-- Container -->
  <LocaleResource>
    <Name>mygarden.container.list.title</Name>
    <Value>Containers</Value>
  </LocaleResource>
  <LocaleResource>
    <Name>mygarden.container.add</Name>
    <Value>Add Container</Value>
  </LocaleResource>
  <LocaleResource>
    <Name>mygarden.container.create.title</Name>
    <Value>New Container</Value>
  </LocaleResource>
  <LocaleResource>
    <Name>mygarden.container.edit.title</Name>
    <Value>Edit Container</Value>
  </LocaleResource>
  <LocaleResource>
    <Name>mygarden.container.list.empty</Name>
    <Value>No containers found.</Value>
  </LocaleResource>
  <LocaleResource>
    <Name>mygarden.container.field.type</Name>
    <Value>Type</Value>
  </LocaleResource>
  <LocaleResource>
    <Name>mygarden.container.field.material</Name>
    <Value>Material</Value>
  </LocaleResource>
  <LocaleResource>
    <Name>mygarden.container.field.color</Name>
    <Value>Color</Value>
  </LocaleResource>
  <LocaleResource>
    <Name>mygarden.container.field.base</Name>
    <Value>Base Circumference</Value>
  </LocaleResource>
  <LocaleResource>
    <Name>mygarden.container.field.rim</Name>
    <Value>Rim Circumference</Value>
  </LocaleResource>
  <LocaleResource>
    <Name>mygarden.container.field.height</Name>
    <Value>Height</Value>
  </LocaleResource>
  <LocaleResource>
    <Name>mygarden.container.field.length</Name>
    <Value>Length</Value>
  </LocaleResource>
  <LocaleResource>
    <Name>mygarden.container.field.width</Name>
    <Value>Width</Value>
  </LocaleResource>
  <LocaleResource>
    <Name>mygarden.container.field.volume</Name>
    <Value>Volume (L)</Value>
  </LocaleResource>
  <LocaleResource>
    <Name>mygarden.container.field.drainage</Name>
    <Value>Has Drainage Hole</Value>
  </LocaleResource>
  <LocaleResource>
    <Name>mygarden.container.inuse.warning</Name>
    <Value>Cannot delete: container is linked to a plant.</Value>
  </LocaleResource>
  <LocaleResource>
    <Name>mygarden.container.linked.plant</Name>
    <Value>Linked Plant</Value>
  </LocaleResource>
</Language>
